hexpot/__init__.py
hexpot/hexpot.py
hexpot/hexpot_pb/__init__.py
hexpot/hexpot_pb/cdformat_pb2.py
hexpot/hexpot_pb/kfinformat_pb2.py
hexpot/hexpot_pb/kstdformat_pb2.py
hexpot-0.5.3.dist-info/LICENSE
hexpot-0.5.3.dist-info/METADATA
hexpot-0.5.3.dist-info/WHEEL
hexpot-0.5.3.dist-info/top_level.txt
hexpot-0.5.3.dist-info/RECORD
