Metadata-Version: 2.1
Name: hexpot
Version: 0.5.3
Summary: Realtime quantitative trading tools
Home-page: https://github.com/onewquant/hexpot
Author: Onew
Author-email: seunghwan0216@gmail.com
License: UNKNOWN
Download-URL: https://github.com/Onewquant/hexpot/archive/master.zip
Keywords: Hexpot,hexpot
Platform: UNKNOWN
Classifier: Programming Language :: Python :: 3
Classifier: Programming Language :: Python :: 3.2
Classifier: Programming Language :: Python :: 3.3
Classifier: Programming Language :: Python :: 3.4
Classifier: Programming Language :: Python :: 3.5
Classifier: Programming Language :: Python :: 3.6
Classifier: Programming Language :: Python :: 3.7
Classifier: Programming Language :: Python :: 3.8
Requires-Python: >=3
Requires-Dist: comtypes (==1.1.7)
Requires-Dist: lxml
Requires-Dist: matplotlib
Requires-Dist: numpy
Requires-Dist: openpyxl
Requires-Dist: pandas
Requires-Dist: protobuf (==3.19.4)
Requires-Dist: pystream-protobuf
Requires-Dist: requests
Requires-Dist: xlrd
Requires-Dist: beautifulsoup4
Requires-Dist: pytz
Requires-Dist: scipy
Requires-Dist: seaborn
Requires-Dist: urllib3
Requires-Dist: websocket-client-py3
Requires-Dist: pyzmq
Requires-Dist: SQLAlchemy
Requires-Dist: pyodbc
Requires-Dist: pywin32
Requires-Dist: pywinauto
Requires-Dist: PyAutoGui
Requires-Dist: PyQt5
Requires-Dist: boto3
Requires-Dist: awscli
Requires-Dist: pykalman
Requires-Dist: plotly
Requires-Dist: scikit-learn
Requires-Dist: hyperopt
Requires-Dist: statsmodels
Requires-Dist: finance-datareader
Requires-Dist: pyupbit
Requires-Dist: python-binance
Requires-Dist: parmap
